luma/__init__.py
luma/lcd/__init__.py
luma/lcd/const.py
luma/lcd/device.py
luma/lcd/segment_mapper.py
luma.lcd-2.10.0.dist-info/LICENSE.rst
luma.lcd-2.10.0.dist-info/METADATA
luma.lcd-2.10.0.dist-info/WHEEL
luma.lcd-2.10.0.dist-info/top_level.txt
luma.lcd-2.10.0.dist-info/RECORD
